[
  {
    "Item": "Tikka Masala - Chicken",
    "Description": "Grilled meat with tikka sauce, yogurt, cream and spices",
    "Price (EUR)": "€11.99",
    "Portuguese Translation": "Frango Tikka Masala"
  },
  {
    "Item": "Tikka Masala - Lamb",
    "Description": "Grilled meat with tikka sauce, yogurt, cream and spices",
    "Price (EUR)": "€12.99",
    "Portuguese Translation": "Borrego Tikka Masala"
  },
  {
    "Item": "Tikka Masala - Prawn",
    "Description": "Grilled meat with tikka sauce, yogurt, cream and spices",
    "Price (EUR)": "€12.99",
    "Portuguese Translation": "Camarão Tikka Masala"
  },
  {
    "Item": "Lababdar - Chicken",
    "Description": "Cooked with onion, tomato, garlic, ginger, coriander and cashew sauce",
    "Price (EUR)": "€11.99",
    "Portuguese Translation": "Frango Lababdar"
  },
  {
    "Item": "Lababdar - Lamb",
    "Description": "Cooked with onion, tomato, garlic, ginger, coriander and cashew sauce",
    "Price (EUR)": "€12.99",
    "Portuguese Translation": "Borrego Lababdar"
  },
  {
    "Item": "Lababdar - Prawn",
    "Description": "Cooked with onion, tomato, garlic, ginger, coriander and cashew sauce",
    "Price (EUR)": "€12.99",
    "Portuguese Translation": "Camarão Lababdar"
  },
  {
    "Item": "Vegetable Curry",
    "Description": "Mixed vegetables cooked in special sauce with spices",
    "Price (EUR)": "€9.99",
    "Portuguese Translation": "Caril de Vegetais"
  },
  {
    "Item": "Daal Tarka",
    "Description": "Three types of lentils cooked in special sauce and spices",
    "Price (EUR)": "€10.99",
    "Portuguese Translation": "Daal Tarka"
  },
  {
    "Item": "Karahi Vegetable",
    "Description": "Mixed vegetables cooked in thick, flavorful sauce",
    "Price (EUR)": "€10.99",
    "Portuguese Translation": "Karahi de Vegetais"
  },
  {
    "Item": "Chana Masala",
    "Description": "Chickpeas cooked with mild spices, onions and tomatoes",
    "Price (EUR)": "€10.99",
    "Portuguese Translation": "Chana Masala"
  },
  {
    "Item": "Coca Cola",
    "Description": "Soft drink",
    "Price (EUR)": "€2.50",
    "Portuguese Translation": "Coca Cola"
  },
  {
    "Item": "Cola Zero",
    "Description": "Soft drink",
    "Price (EUR)": "€2.50",
    "Portuguese Translation": "Cola Zero"
  },
  {
    "Item": "Fanta",
    "Description": "Soft drink",
    "Price (EUR)": "€2.50",
    "Portuguese Translation": "Fanta"
  },
  {
    "Item": "Icetea (Lemon, Mango, Peach)",
    "Description": "Flavored iced tea",
    "Price (EUR)": "€2.50",
    "Portuguese Translation": "Icetea (Limão, Manga, Pêssego)"
  },
  {
    "Item": "Sparkling Water",
    "Description": "Mineral water with gas",
    "Price (EUR)": "€2.50",
    "Portuguese Translation": "Água Com Gás"
  },
  {
    "Item": "Water 50cl",
    "Description": "Still water",
    "Price (EUR)": "€2.00",
    "Portuguese Translation": "Água 50cl"
  },
  {
    "Item": "Water 1.5L",
    "Description": "Still water",
    "Price (EUR)": "€2.99",
    "Portuguese Translation": "Água 1.5L"
  },
  {
    "Item": "Beer - Imperial",
    "Description": "Draft beer",
    "Price (EUR)": "€2.00",
    "Portuguese Translation": "Cerveja Imperial"
  },
  {
    "Item": "Beer - Mug",
    "Description": "Beer served in a mug",
    "Price (EUR)": "€3.50",
    "Portuguese Translation": "Caneca de Cerveja"
  },
  {
    "Item": "Nepalese Beer",
    "Description": "Imported beer from Nepal",
    "Price (EUR)": "€2.99",
    "Portuguese Translation": "Cerveja Nepalesa"
  },
  {
    "Item": "Indian Beer",
    "Description": "Imported beer from India",
    "Price (EUR)": "€3.50",
    "Portuguese Translation": "Cerveja Indiana"
  },
  {
    "Item": "Somersby",
    "Description": "Cider",
    "Price (EUR)": "€2.99",
    "Portuguese Translation": "Somersby"
  },
  {
    "Item": "Glass of Wine (White/Red)",
    "Description": "House wine",
    "Price (EUR)": "€3.50",
    "Portuguese Translation": "Copo de Vinho (Branco/Tinto)"
  },
  {
    "Item": "Plain Lassi",
    "Description": "Traditional yogurt drink",
    "Price (EUR)": "€2.50",
    "Portuguese Translation": "Lassi Natural"
  },
  {
    "Item": "Mango Lassi",
    "Description": "Special yogurt drink with mango",
    "Price (EUR)": "€3.50",
    "Portuguese Translation": "Mango Lassi"
  },
  {
    "Item": "Butter Naan",
    "Description": "Leavened bread baked in the tandoor and brushed with butter",
    "Price (EUR)": "€2.99",
    "Portuguese Translation": "Pão Indiano com Manteiga"
  },
  {
    "Item": "Garlic Naan",
    "Description": "Leavened tandoori bread with fire-roasted garlic and coriander",
    "Price (EUR)": "€3.99",
    "Portuguese Translation": "Pão Indiano com Alho"
  },
  {
    "Item": "Cheese Naan",
    "Description": "Leavened bread baked in the tandoor with cheese and coriander leaves",
    "Price (EUR)": "€4.50",
    "Portuguese Translation": "Pão Indiano com Queijo"
  },
  {
    "Item": "Cheese & Garlic Naan",
    "Description": "Leavened bread baked in the tandoor with cheese, garlic and coriander",
    "Price (EUR)": "€5.50",
    "Portuguese Translation": "Pão Indiano com Queijo e Alho"
  },
  {
    "Item": "Mixed Salad",
    "Description": "Cucumber, lettuce, tomato, onion, carrots & olives",
    "Price (EUR)": "€5.99",
    "Portuguese Translation": "Salada Mista"
  },
  {
    "Item": "Coffee",
    "Description": "Hot beverage",
    "Price (EUR)": "€0.99",
    "Portuguese Translation": "Café"
  },
  {
    "Item": "PAPARI/PAPADUM",
    "Description": "A THIN CRISPY INDIAN FLATBREAD",
    "Price (EUR)": "€1.20",
    "Portuguese Translation": "PAPARI/PAPADUM"
  },
  {
    "Item": "VEG. SAMOSA",
    "Description": "A CRISPY TRIANGULAR PASTRY STUFFED WITH SAVORY VEGETABLES",
    "Price (EUR)": "€1.95",
    "Portuguese Translation": "CHAMUÇA VEGETARIANA"
  },
  {
    "Item": "CHICKEN SAMOSA",
    "Description": "A POPULAR CRISPY PASTRY STUFFED WITH CHICKEN MEAT",
    "Price (EUR)": "€2.20",
    "Portuguese Translation": "CHAMUÇA DE FRANGO"
  },
  {
    "Item": "ONION BHAJI",
    "Description": "A TRADITIONAL INDIAN SNACK: CHOPPED ONION WRAPPED IN CHICKPEA BATTER AND DEEP FRIED",
    "Price (EUR)": "€4.50",
    "Portuguese Translation": "PASTÉIS DE CEBOLA"
  },
  {
    "Item": "PANEER PAKORA",
    "Description": "AROMATIZADAS E FRITO SLICES OF INDIAN CHEESE (PANEER) WRAPPED IN GRAM FLOUR, SPICES AND DEEP FRIED",
    "Price (EUR)": "€6.99",
    "Portuguese Translation": "PASTÉIS QUEIJO INDIANO"
  },
  {
    "Item": "CHICKEN PAKORA",
    "Description": "AROMATIZADOS E FRITOS BONELESS CHICKEN SEASONED, WRAPPED IN GRAM FLOUR, SPICES AND DEEP FRIED",
    "Price (EUR)": "€5.99",
    "Portuguese Translation": "PASTÉIS DE FRANGO"
  },
  {
    "Item": "NAMASTE CURRY HOUSE ENTRADA MISTA VEG + CARNE",
    "Description": "NAMASTE CURRY HOUSE MIXED STARTERS-VEG & NON-VEG",
    "Price (EUR)": "€12.99",
    "Portuguese Translation": "NAMASTE CURRY HOUSE ENTRADA MISTA VEG + CARNE"
  },
  {
    "Item": "VEG BIRYANI",
    "Description": "BASMATI RICE COOKED WITH MIXED VEGETABLES, CASHEW NUTS, RAISINS, HERBS AND MILD SPICES",
    "Price (EUR)": "€10.99",
    "Portuguese Translation": "VEG BIRYANI"
  },
  {
    "Item": "CHICKEN BIRYANI",
    "Description": "BASMATI RICE WITH CHICKEN, EGG, CASHEW NUTS, HERBS AND MILD SPICES",
    "Price (EUR)": "€11.99",
    "Portuguese Translation": "CHICKEN BIRYANI"
  },
  {
    "Item": "LAMB BIRYANI",
    "Description": "ERVAS, MOLHO ESPECIAL E ESPECIARIAS SUAVES BASMATI RICE WITH LAMB, CASHEW NUTS, HERBS AND MILD SPICES",
    "Price (EUR)": "€12.99",
    "Portuguese Translation": "LAMB BIRYANI"
  },
  {
    "Item": "CHICKEN TIKKA BIRYANI",
    "Description": "CAJU, ERVAS, MOLHO ESPECIAL E ESPECIARIAS SUAVES BASMATI RICE WITH GRILLED CHICKEN, CASHEW NUTS, HERBS AND SPICES",
    "Price (EUR)": "€13.99",
    "Portuguese Translation": "CHICKEN TIKKA BIRYANI"
  },
  {
    "Item": "PLAIN RICE",
    "Description": "PLAIN RICE",
    "Price (EUR)": "€2.99",
    "Portuguese Translation": "ARROZ BRANCO BASMATI"
  },
  {
    "Item": "ARROZ BASMATI COM COMINHOS",
    "Description": "JEERA RICE WITH CUMIN",
    "Price (EUR)": "€3.75",
    "Portuguese Translation": "ARROZ BASMATI COM COMINHOS"
  },
  {
    "Item": "PULAO RICE",
    "Description": "RICE WITH CUMIN, CASHEW NUTS AND PEAS",
    "Price (EUR)": "€3.99",
    "Portuguese Translation": "ARROZ PULAO"
  },
  {
    "Item": "EGG RICE",
    "Description": "EGG RICE",
    "Price (EUR)": "€3.99",
    "Portuguese Translation": "ARROZ COM OVO"
  },
  {
    "Item": "CARNE",
    "Description": "CARNE",
    "Price (EUR)": "€12.99",
    "Portuguese Translation": "CARNE"
  },
  {
    "Item": "NAMASTE MIX CURRY",
    "Description": "PRAWN, CHICKEN AND LAMB COOKED IN MILD SAUCE WITH HERBS AND SPICES",
    "Price (EUR)": "€13.99",
    "Portuguese Translation": "NAMASTE MISTA CARIL"
  },
  {
    "Item": "NAMASTE MIX BIRYANI",
    "Description": "BASMATI RICE COOKED WITH SHRIMP, CHICKEN AND LAMB, FLAVORED WITH SPICES",
    "Price (EUR)": "€13.99",
    "Portuguese Translation": "NAMASTE MIX BIRYANI"
  },
  {
    "Item": "TANDOORI CHICKEN",
    "Description": "TANDOOR HALF CHICKEN MARINATED IN AROMATIC SPICES AND GRILLED IN A TANDOOR",
    "Price (EUR)": "€12.99",
    "Portuguese Translation": "TANDOORI CHICKEN"
  },
  {
    "Item": "CHICKEN TIKKA",
    "Description": "TANDOOR CHICKEN BREAST MARINATED WITH SPICES AND GRILLED IN THE TANDOOR",
    "Price (EUR)": "€12.99",
    "Portuguese Translation": "CHICKEN TIKKA"
  },
  {
    "Item": "PANEER TIKKA",
    "Description": "TANDOOR INDIAN COTTAGE CHEESE MARINATED IN YOGURT, HERBS AND SPICES, GRILLED IN THE TANDOOR",
    "Price (EUR)": "€12.99",
    "Portuguese Translation": "PANEER TIKKA"
  },
  {
    "Item": "MURG MALAI TIKKA",
    "Description": "TANDOOR CHICKEN BREAST WRAPPED IN CHEESE AND CREAM, GRILLED IN THE TANDOOR",
    "Price (EUR)": "€13.99",
    "Portuguese Translation": "MURG MALAI TIKKA"
  }
]